alloconda/__init__.py
alloconda/build_backend.py
alloconda/cli.py
alloconda/cli_build.py
alloconda/cli_develop.py
alloconda/cli_helpers.py
alloconda/cli_init.py
alloconda/cli_inspect.py
alloconda/cli_python.py
alloconda/cli_wheel.py
alloconda/cli_wheel_all.py
alloconda/pbs.py
alloconda/templates/build.zig.j2
alloconda/templates/build.zig.zon.j2
alloconda/templates/root.zig.j2
alloconda/wheel_builder.py
alloconda-0.0.1a8.dist-info/licenses/LICENSE
alloconda-0.0.1a8.dist-info/WHEEL
alloconda-0.0.1a8.dist-info/entry_points.txt
alloconda-0.0.1a8.dist-info/METADATA
alloconda-0.0.1a8.dist-info/RECORD
