Metadata-Version: 2.4
Name: alloconda
Version: 0.0.1a8
Summary: Zig-first Python extensions with cross-compiled wheels
Keywords: zig,python,extension,build,wheel,pep-517
Author: Matt Robenolt
Author-email: Matt Robenolt <m@robenolt.com>
License-Expression: Apache-2.0
License-File: LICENSE
Classifier: Development Status :: 3 - Alpha
Classifier: Environment :: Console
Classifier: Programming Language :: Python :: 3
Classifier: Programming Language :: Python :: 3.14
Classifier: Topic :: Software Development :: Build Tools
Requires-Dist: click>=8.3.1
Requires-Dist: httpx>=0.28.1
Requires-Dist: jinja2>=3.1.4
Requires-Dist: lief>=0.17.1
Requires-Dist: tomlkit>=0.13.3
Requires-Python: >=3.14
Project-URL: Homepage, https://github.com/mattrobenolt/alloconda
Project-URL: Issues, https://github.com/mattrobenolt/alloconda/issues
Project-URL: Repository, https://github.com/mattrobenolt/alloconda
